setup.py
lettherebe/__init__.py
lettherebe/ccwrapper.py
lettherebe/handler.py
lettherebe/main.py
lettherebe/package_languages.py
lettherebe/registry.py
lettherebe/repository_hosts.py
lettherebe/services.py
lettherebe/utils.py
lettherebe.egg-info/PKG-INFO
lettherebe.egg-info/SOURCES.txt
lettherebe.egg-info/dependency_links.txt
lettherebe.egg-info/entry_points.txt
lettherebe.egg-info/requires.txt
lettherebe.egg-info/top_level.txt