Metadata-Version: 1.1
Name: lettherebe
Version: 0.0.2
Summary: LetThereBe Python library and command-line scripts
Home-page: https://github.com/LetThereBe/lettherebe
Author: Mayeul d'Avezac, Ilektra Christidi, Alice Harpole, David Perez Suarez, Thomas Robitaille, Sinan Shi
Author-email: thomas.robitaille@gmail.com
License: BSD
Platform: UNKNOWN
Classifier: Development Status :: 1 - Planning
Classifier: Programming Language :: Python
Classifier: Programming Language :: Python :: 2
Classifier: Programming Language :: Python :: 3
Classifier: Operating System :: OS Independent
Classifier: License :: OSI Approved :: BSD License
